MANIFEST.in
README
requirements.txt
setup.cfg
setup.py
docs/README
docs/actions.rst
docs/changelog.rst
docs/conf.py
docs/index.rst
docs/make_actions_rst.py
docs/packaging.rst
docs/releasing.rst
docs/remote.rst
docs/assets/favicon.ico
docs/assets/nature.css
docs/assets/selenium-hexafluoride.png
docs/assets/sst-logo.png
docs/assets/sst-logo_black.png
docs/assets/sst-logo_small.png
examples/googlefinance.py
examples/seleniumhq.py
examples/test_ubuntu.py
examples/yahoofinance.py
src/sst/__init__.py
src/sst/actions.py
src/sst/browsers.py
src/sst/cases.py
src/sst/command.py
src/sst/concurrency.py
src/sst/config.py
src/sst/context.py
src/sst/filters.py
src/sst/loaders.py
src/sst/results.py
src/sst/runtests.py
src/sst/xvfbdisplay.py
src/sst.egg-info/PKG-INFO
src/sst.egg-info/SOURCES.txt
src/sst.egg-info/dependency_links.txt
src/sst.egg-info/entry_points.txt
src/sst.egg-info/requires.txt
src/sst.egg-info/top_level.txt
src/sst/scripts/__init__.py
src/sst/scripts/remote.py
src/sst/scripts/run.py
src/sst/scripts/test.py
src/sst/selftests/__init__.py
src/sst/selftests/_ignored.py
src/sst/selftests/_module.py
src/sst/selftests/_test.py
src/sst/selftests/alerts.py
src/sst/selftests/assert_element.py
src/sst/selftests/assert_text.py
src/sst/selftests/assert_urls.py
src/sst/selftests/attribute.py
src/sst/selftests/button.py
src/sst/selftests/by_css.py
src/sst/selftests/by_xpath.py
src/sst/selftests/checkbox.py
src/sst/selftests/click.py
src/sst/selftests/context.py
src/sst/selftests/cookies.py
src/sst/selftests/css_props.py
src/sst/selftests/current_url.py
src/sst/selftests/data_driven_form.csv
src/sst/selftests/data_driven_form.py
src/sst/selftests/element_to_string.py
src/sst/selftests/endtest.py
src/sst/selftests/equal.py
src/sst/selftests/execute_script.py
src/sst/selftests/exists_element.py
src/sst/selftests/file_input.py
src/sst/selftests/flags.py
src/sst/selftests/get_element.py
src/sst/selftests/get_element_fails.py
src/sst/selftests/get_element_text_regex.py
src/sst/selftests/go_browser.py
src/sst/selftests/html5.py
src/sst/selftests/is_displayed.py
src/sst/selftests/keys.py
src/sst/selftests/link.py
src/sst/selftests/no_js.py
src/sst/selftests/radio.py
