Metadata-Version: 1.1
Name: sst
Version: 0.2.4
Summary: SST - Web Test Framework
Home-page: http://testutils.org/sst
Author: Canonical Online Services Team
Author-email: cgoldberg _at_ gmail.com
License: UNKNOWN
Keywords: selenium,webdriver,test,testing,web,automation
Platform: UNKNOWN
Classifier: Development Status :: 4 - Beta
Classifier: Environment :: Console
Classifier: Environment :: Web Environment
Classifier: Intended Audience :: Developers
Classifier: License :: OSI Approved :: Apache Software License
Classifier: Programming Language :: Python
Classifier: Programming Language :: Python :: 2
Classifier: Programming Language :: Python :: 2.6
Classifier: Programming Language :: Python :: 2.7
Classifier: Operating System :: OS Independent
Classifier: Topic :: Software Development :: Libraries
Classifier: Topic :: Software Development :: Libraries :: Python Modules
Classifier: Topic :: Software Development :: Testing
Classifier: Topic :: Internet :: WWW/HTTP :: Browsers
